ax56/__init__.py
ax56-0.1.0.dist-info/LICENSE
ax56-0.1.0.dist-info/METADATA
ax56-0.1.0.dist-info/WHEEL
ax56-0.1.0.dist-info/top_level.txt
ax56-0.1.0.dist-info/RECORD
